satflow/__init__.py
satflow/__main__.py
satflow/cli.py
satflow/data/.gitkeep
satflow/data/README.md
satflow/data.py
satflow/py.typed
satisfactory_flow-0.1.0.dist-info/METADATA
satisfactory_flow-0.1.0.dist-info/WHEEL
satisfactory_flow-0.1.0.dist-info/entry_points.txt
satisfactory_flow-0.1.0.dist-info/licenses/LICENSE
satisfactory_flow-0.1.0.dist-info/RECORD
