Metadata-Version: 2.4
Name: satisfactory-flow
Version: 0.1.0
Summary: Automate your automations. Production flow calculations for Satisfactory.
License-File: LICENSE
Keywords: module,packaging,single-file
Author: Apathetic Tools
Requires-Python: >=3.14
Classifier: Development Status :: 3 - Alpha
Classifier: Environment :: Console
Classifier: Intended Audience :: End Users/Desktop
Classifier: Operating System :: OS Independent
Classifier: Programming Language :: Python :: 3
Classifier: Programming Language :: Python :: 3 :: Only
Classifier: Programming Language :: Python :: 3.14
Classifier: Topic :: Games/Entertainment :: Simulation
Requires-Dist: platformdirs (>=4.5.1,<5.0.0)
Project-URL: Changelog, https://github.com/apathetic-tools/satflow/releases
Project-URL: Documentation, https://apathetic-tools.github.io/satflow/
Project-URL: Homepage, https://github.com/apathetic-tools/satflow
Project-URL: Issues, https://github.com/apathetic-tools/satflow/issues
Project-URL: Repository, https://github.com/apathetic-tools/satflow
